{"cookies": [{"name": "PLAY_SESSION", "value": "401ad73e6c57e7b38ddfbc6f3c89e6f6caaa85e7-risepoint_pSessionId=pg5r4tj6eoh7cj0sivhfqher0b&instance=vps-2-558f574bd6-pncl6", "domain": "risepoint.wd503.myworkdayjobs.com", "path": "/", "expires": -1, "httpOnly": true, "secure": true, "sameSite": "Lax"}, {"name": "wd-browser-id", "value": "050ce04e-0bd5-4d1a-afd2-ab04ad05863e", "domain": "risepoint.wd503.myworkdayjobs.com", "path": "/", "expires": -1, "httpOnly": true, "secure": true, "sameSite": "Lax"}, {"name": "CALYPSO_CSRF_TOKEN", "value": "17d96f0c-3080-4cac-ab68-ce636f426176", "domain": "risepoint.wd503.myworkdayjobs.com", "path": "/", "expires": -1, "httpOnly": true, "secure": true, "sameSite": "Lax"}, {"name": "CALYPSO_SESSION", "value": "cb15cb89-fa81-4df9-ab3b-d4889b0f02bc.cmlzZXBvaW50.V0RDQzEuMIQAJQAAIMWNZnYUNGJe7g44oHc24lJFYyhxdAwOvdCn0I88tBj7AACMABYBMQAQH3eCeOnTdXuePlm4BqodHgAAAGNiMTVjYjg5LWZhODEtNGRmOS1hYjNiLWQ0ODg5YjBmMDJiYw==", "domain": "risepoint.wd503.myworkdayjobs.com", "path": "/", "expires": -1, "httpOnly": true, "secure": true, "sameSite": "Lax"}, {"name": "vps-cke", "value": "\"e15d9f7446363d7c\"", "domain": "risepoint.wd503.myworkdayjobs.com", "path": "/", "expires": -1, "httpOnly": true, "secure": true, "sameSite": "None"}, {"name": "__cf_bm", "value": "2nws8Ctqt63biYuSxSUB6b0Sr4.9.CH001u2jPoeZEk-1778736858.012449-1.0.1.1-W9ipug.uRKX.NgpMK34sqPnA.M3dOodkMJ0ixl_uzpBPBTlZdPINa7MrhcRq77131vGRRbyG202thjPu10Xg98DEQ76e5km1b.ImCK47jV5mAwyLmiD8uLJVNuXv9au8", "domain": ".risepoint.wd503.myworkdayjobs.com", "path": "/", "expires": 1778738658.314083, "httpOnly": true, "secure": true, "sameSite": "None"}, {"name": "_cfuvid", "value": "Tl_HDn09HfUqw6F4KP.99At3WyEctxSU6gqPF.wLN3w-1778736858.012449-1.0.1.1-WvUJvsKeNNO8Z_bGTYAWx4y3XaIikCQmyeoi8KEy2zA", "domain": ".risepoint.wd503.myworkdayjobs.com", "path": "/", "expires": -1, "httpOnly": true, "secure": true, "sameSite": "None"}, {"name": "__cf_bm", "value": "vghmR1vcjqqQ73T5VzjZVcaNWnkSt5zip7ynAWhNChI-1778736858.8448195-1.0.1.1-5T_pumgDfb68Eb5v.L4gwF8dlI1zf6EuwrHIr6np_MOAAQKbGCDUm_zi8u_nZUcaKK8nhrVrveZ4M2GKZI1S91fDS1qwsK2p.EgqGT0zGrRUBx7rQ1aZUTdDaE5pA7xz", "domain": ".wd503.myworkday.com", "path": "/", "expires": 1778738658.761496, "httpOnly": true, "secure": true, "sameSite": "None"}, {"name": "__cf_bm", "value": "_Qup7uXU2J2XI.2qoa4T4vVOyLhplq6B0DGprERFE6U-1778736860.0557292-1.0.1.1-7oafqmHZAM2415XTKOGlwEoSZ1yIbPAXPhqhqadQ_kb0ZKo4HnLbO9Jl6BIuBBO1xKLkXr4F9QZVeX1RYc1d17HzZ00djmt1DVVF7Fo9yQQiqJSekZzS6hiVTdmw8R39", "domain": ".myworkdaycdn.com", "path": "/", "expires": 1778738660.086512, "httpOnly": true, "secure": true, "sameSite": "None"}, {"name": "timezoneOffset", "value": "-330", "domain": "risepoint.wd503.myworkdayjobs.com", "path": "/", "expires": -1, "httpOnly": false, "secure": true, "sameSite": "Lax"}], "origins": []}